compose_micromanager-0.3.4.dist-info/licenses/LICENSE
micromanager/__init__.py
micromanager/main.py
micromanager/models.py
micromanager/commands/__init__.py
micromanager/commands/app.py
micromanager/commands/config.py
micromanager/commands/errors.py
micromanager/commands/restart.py
micromanager/commands/start.py
micromanager/commands/status.py
micromanager/commands/stop.py
micromanager/commands/use.py
micromanager/commands/utils.py
micromanager/compose/__init__.py
micromanager/compose/down.py
micromanager/compose/errors.py
micromanager/compose/ps.py
micromanager/compose/restart.py
micromanager/compose/up.py
micromanager/config/__init__.py
micromanager/config/app.py
micromanager/config/config.py
micromanager/config/errors.py
micromanager/config/models.py
micromanager/config/parser.py
compose_micromanager-0.3.4.dist-info/METADATA
compose_micromanager-0.3.4.dist-info/WHEEL
compose_micromanager-0.3.4.dist-info/entry_points.txt
compose_micromanager-0.3.4.dist-info/top_level.txt
compose_micromanager-0.3.4.dist-info/RECORD
