Metadata-Version: 2.4
Name: compose-micromanager
Version: 0.3.4
Summary: CLI application to manage microservices with docker-compose
Requires-Python: >=3.10
License-File: LICENSE
Requires-Dist: platformdirs>=4.3.8
Requires-Dist: python-on-whales>=0.78.0
Requires-Dist: pyyaml>=6.0.2
Requires-Dist: record-list>=0.1.0
Requires-Dist: typer>=0.16.0
Dynamic: license-file
